Metadata-Version: 2.1
Name: precursion
Version: 1.0.0
Summary: No more `RecursionError: maximum recursion depth exceeded`
Home-page: https://github.com/python273/precursion
Author: python273
Author-email: whoami@python273.pw
License: MIT
Download-URL: https://github.com/python273/precursion/archive/v1.0.0.zip
Platform: UNKNOWN
Classifier: License :: OSI Approved :: MIT License
Classifier: Operating System :: OS Independent
Classifier: Programming Language :: Python
Classifier: Programming Language :: Python :: 2
Classifier: Programming Language :: Python :: 2.7
Classifier: Programming Language :: Python :: 3
Classifier: Programming Language :: Python :: 3.4
Classifier: Programming Language :: Python :: 3.5
Classifier: Programming Language :: Python :: 3.6
Classifier: Programming Language :: Python :: Implementation :: PyPy
Classifier: Programming Language :: Python :: Implementation :: CPython
